{"cameraMode":{"drawMode":0,"name":"Shaded","section":"Shading Mode"},"sceneLighting":true,"audioPlay":false,"sceneViewState":{"m_AlwaysRefresh":false,"showFog":true,"showSkybox":true,"showFlares":true,"showImageEffects":true,"showParticleSystems":true,"showVisualEffectGraphs":true,"m_FxEnabled":true},"in2DMode":false,"pivot":{"x":13.032066345214844,"y":-2.7069473266601564,"z":1.891690731048584},"rotation":{"x":-0.24761585891246797,"y":0.7300493717193604,"z":-0.33288273215293887,"w":-0.5430498123168945},"size":10.0,"orthographic":false}